ipywebcam/__init__.py
ipywebcam/_frontend.py
ipywebcam/_version.py
ipywebcam/common.py
ipywebcam/easyqueue.py
ipywebcam/recorder.py
ipywebcam/webcam.py
ipywebcam/labextension/build_log.json
ipywebcam/labextension/package.json
ipywebcam/labextension/static/lib_index_js.9c3b5fbf4b9efeeb7001.js
ipywebcam/labextension/static/lib_index_js.9c3b5fbf4b9efeeb7001.js.map
ipywebcam/labextension/static/lib_plugin_js.0d80ab6fa0ba98b64288.js
ipywebcam/labextension/static/lib_plugin_js.0d80ab6fa0ba98b64288.js.map
ipywebcam/labextension/static/lib_recorder_js-lib_webcam_js.275832bf8946eb51678f.js
ipywebcam/labextension/static/lib_recorder_js-lib_webcam_js.275832bf8946eb51678f.js.map
ipywebcam/labextension/static/lib_recorder_js-lib_webcam_js.693d71182b779b69c197.js
ipywebcam/labextension/static/lib_recorder_js-lib_webcam_js.693d71182b779b69c197.js.map
ipywebcam/labextension/static/remoteEntry.828eab486061c527aa60.js
ipywebcam/labextension/static/remoteEntry.828eab486061c527aa60.js.map
ipywebcam/labextension/static/remoteEntry.ed0f48052e5724472c6b.js.map
ipywebcam/labextension/static/style.js
ipywebcam/labextension/static/vendors-node_modules_lru-cache_index_mjs.74a6083355191dd51e49.js
ipywebcam/labextension/static/vendors-node_modules_lru-cache_index_mjs.74a6083355191dd51e49.js.map
ipywebcam/nbextension/extension.js
ipywebcam/nbextension/index.js
ipywebcam/nbextension/index.js.map
ipywebcam/tests/__init__.py
ipywebcam/tests/conftest.py
ipywebcam/tests/test_nbextension_path.py
ipywebcam/tests/test_webcam.py
ipywebcam-0.1.16.data/data/share/jupyter/labextensions/ipywebcam/build_log.json
ipywebcam-0.1.16.data/data/share/jupyter/labextensions/ipywebcam/package.json
ipywebcam-0.1.16.data/data/share/jupyter/labextensions/ipywebcam/static/lib_index_js.9c3b5fbf4b9efeeb7001.js
ipywebcam-0.1.16.data/data/share/jupyter/labextensions/ipywebcam/static/lib_index_js.9c3b5fbf4b9efeeb7001.js.map
ipywebcam-0.1.16.dist-info/METADATA
ipywebcam-0.1.16.dist-info/WHEEL
ipywebcam-0.1.16.dist-info/licenses/LICENSE.txt
ipywebcam-0.1.16.dist-info/RECORD
